setup.py
normalbinomial_distributions/Binomialdistribution.py
normalbinomial_distributions/Gaussiandistribution.py
normalbinomial_distributions/Generaldistribution.py
normalbinomial_distributions/__init__.py
normalbinomial_distributions.egg-info/PKG-INFO
normalbinomial_distributions.egg-info/SOURCES.txt
normalbinomial_distributions.egg-info/dependency_links.txt
normalbinomial_distributions.egg-info/not-zip-safe
normalbinomial_distributions.egg-info/top_level.txt