Metadata-Version: 1.0
Name: normalbinomial-distributions
Version: 0.1
Summary: Gaussian and Binomial distributions
Home-page: UNKNOWN
Author: David Babalola
Author-email: oredavid14@gmail.com
License: UNKNOWN
Platform: UNKNOWN
